eventpipe/__init__.py
eventpipe/client.py
eventpipe/config.py
eventpipe_python_client-0.1.0.dist-info/DESCRIPTION.rst
eventpipe_python_client-0.1.0.dist-info/METADATA
eventpipe_python_client-0.1.0.dist-info/RECORD
eventpipe_python_client-0.1.0.dist-info/WHEEL
eventpipe_python_client-0.1.0.dist-info/metadata.json
eventpipe_python_client-0.1.0.dist-info/top_level.txt
