Metadata-Version: 2.0
Name: eventpipe-python-client
Version: 0.1.0
Summary: A Python client to the Event Pipe
Home-page: https://github.com/bcambel/event-pipe-client-py/
Author: Bahadir Cambel
Author-email: bcambel@gmail.com
License: Unlicense
Platform: any
Classifier: Development Status :: 4 - Beta
Classifier: Environment :: Web Environment
Classifier: Intended Audience :: Developers
Classifier: License :: OSI Approved :: MIT License
Classifier: Operating System :: OS Independent
Classifier: Programming Language :: Python
Classifier: Programming Language :: Python :: 2
Classifier: Programming Language :: Python :: 2.6
Classifier: Programming Language :: Python :: 2.7
Classifier: Topic :: Software Development :: Libraries :: Python Modules
Requires-Dist: requests (>=2.13.0)
